cntm/__init__.py
cntm/linkbert.py
cntm/main.py
cntm/text_processing.py
cntm/topic_representation.py
cntm-0.0.1.dist-info/LICENSE
cntm-0.0.1.dist-info/METADATA
cntm-0.0.1.dist-info/WHEEL
cntm-0.0.1.dist-info/top_level.txt
cntm-0.0.1.dist-info/RECORD
